lsh/__init__.py
lsh/cMinhash.cpython-37m-darwin.so
lsh/cache.py
lsh/minhash.py
hlwy_lsh-0.3.0.dist-info/LICENSE
hlwy_lsh-0.3.0.dist-info/METADATA
hlwy_lsh-0.3.0.dist-info/WHEEL
hlwy_lsh-0.3.0.dist-info/top_level.txt
hlwy_lsh-0.3.0.dist-info/RECORD
