Metadata-Version: 2.1
Name: hlwy-lsh
Version: 0.3.0
Summary: A library for performing shingling and LSH for python.
Home-page: https://github.com/feynmanlabs/hlwy-lsh
Author: Matti Lyra
Author-email: matti.lyra@gmail.com
License: MIT
Platform: UNKNOWN
Classifier: License :: OSI Approved :: MIT License
Classifier: Programming Language :: Python
Classifier: Programming Language :: Python :: 3
Classifier: Programming Language :: Python :: 3.7
Classifier: Programming Language :: Python :: Implementation :: CPython
Requires-Dist: numpy
